genmechanics/__init__.py
genmechanics/core.py
genmechanics/geometry.py
genmechanics/linkages.py
genmechanics/tools.py
genmechanics-0.0.4.dist-info/DESCRIPTION.rst
genmechanics-0.0.4.dist-info/METADATA
genmechanics-0.0.4.dist-info/RECORD
genmechanics-0.0.4.dist-info/WHEEL
genmechanics-0.0.4.dist-info/metadata.json
genmechanics-0.0.4.dist-info/top_level.txt
