Metadata-Version: 2.0
Name: genmechanics
Version: 0.0.4
Summary: General mechanics solver for python
Home-page: http://github.com/masfaraud/genmechanics
Author: Steven Masfaraud
Author-email: steven@masfaraud.fr
License: Creative Commons Attribution-Share Alike license
Keywords: General mechanics
Platform: UNKNOWN
Classifier: Topic :: Scientific/Engineering
Classifier: Development Status :: 3 - Alpha
Requires-Dist: matplotlib
Requires-Dist: networkx
Requires-Dist: numpy
Requires-Dist: scipy
